LICENSE
MANIFEST.in
README.md
pyproject.toml
setup.cfg
setup.py
syncthing/__init__.py
syncthing/meta.py
syncthing.egg-info/PKG-INFO
syncthing.egg-info/SOURCES.txt
syncthing.egg-info/dependency_links.txt
syncthing.egg-info/requires.txt
syncthing.egg-info/top_level.txt
syncthing.egg-info/zip-safe